{
  "query_id": "751",
  "timestamp": "2025-10-22T16:12:45.962497",
  "model": "Presidio-2.2.360",
  "analyzer_config": {
    "language": "en",
    "score_threshold": 0.35,
    "custom_recognizers": [
      "MedicalRecordNumberRecognizer",
      "UniqueIdentifierRecognizer"
    ]
  },
  "original_query": "Best practices for managing hypertension in a 65-year-old male, William R. seen at St. Mary's Hospital on July 10th, 2023 (MRN: #SMH12345)?",
  "ground_truth_phi": "NAME: William R. | GEOGRAPHIC_LOCATION: St. Mary's Hospital | DATE: July 10th, 2023 | MEDICAL_RECORD_NUMBER: #SMH12345",
  "ground_truth_phi_count": 4,
  "presidio_output": "Best practices for managing hypertension in a [REDACTED_DATE] male, [REDACTED_NAME] seen at [REDACTED_GEOGRAPHIC_LOCATION] on [REDACTED_DATE] (MRN: #SMH12345)?",
  "presidio_entities_detected": [
    {
      "entity_type": "DATE_TIME",
      "hipaa_category": "DATE",
      "start": 46,
      "end": 57,
      "score": 0.85,
      "text": "65-year-old",
      "recognizer": "SpacyRecognizer"
    },
    {
      "entity_type": "PERSON",
      "hipaa_category": "NAME",
      "start": 64,
      "end": 74,
      "score": 0.85,
      "text": "William R.",
      "recognizer": "SpacyRecognizer"
    },
    {
      "entity_type": "LOCATION",
      "hipaa_category": "GEOGRAPHIC_LOCATION",
      "start": 83,
      "end": 102,
      "score": 0.85,
      "text": "St. Mary's Hospital",
      "recognizer": "SpacyRecognizer"
    },
    {
      "entity_type": "DATE_TIME",
      "hipaa_category": "DATE",
      "start": 106,
      "end": 121,
      "score": 0.85,
      "text": "July 10th, 2023",
      "recognizer": "SpacyRecognizer"
    }
  ],
  "leak_detection": {
    "leaked_phi_count": 1,
    "leaked_phi_details": [
      {
        "type": "MEDICAL_RECORD_NUMBER",
        "value": "#SMH12345",
        "start": 128,
        "end": 137
      }
    ],
    "status": "LEAK_DETECTED"
  },
  "metrics": {
    "total_phi_entities": 4,
    "successfully_redacted": 3,
    "leaked_failures": 1,
    "total_detected": 4,
    "recall": "0.7500",
    "precision": "0.7500",
    "f1_score": "0.7500"
  }
}