{
  "query_id": "613",
  "timestamp": "2025-10-22T16:12:45.276899",
  "model": "Presidio-2.2.360",
  "analyzer_config": {
    "language": "en",
    "score_threshold": 0.35,
    "custom_recognizers": [
      "MedicalRecordNumberRecognizer",
      "UniqueIdentifierRecognizer"
    ]
  },
  "original_query": "info on carb counting for insulin-dependent diabetic pt, Kevin R., seen at our 5th avenue clinic, needs recs before next appt on 12th Jan 2023.",
  "ground_truth_phi": "NAME: Kevin R. | GEOGRAPHIC_LOCATION: 5th avenue clinic | DATE: 12th Jan 2023",
  "ground_truth_phi_count": 3,
  "presidio_output": "info on carb counting for insulin-dependent diabetic pt, [REDACTED_NAME], seen at our 5th avenue clinic, needs recs before next appt on [REDACTED_DATE].",
  "presidio_entities_detected": [
    {
      "entity_type": "PERSON",
      "hipaa_category": "NAME",
      "start": 57,
      "end": 65,
      "score": 0.85,
      "text": "Kevin R.",
      "recognizer": "SpacyRecognizer"
    },
    {
      "entity_type": "DATE_TIME",
      "hipaa_category": "DATE",
      "start": 129,
      "end": 142,
      "score": 0.85,
      "text": "12th Jan 2023",
      "recognizer": "SpacyRecognizer"
    }
  ],
  "leak_detection": {
    "leaked_phi_count": 1,
    "leaked_phi_details": [
      {
        "type": "GEOGRAPHIC_LOCATION",
        "value": "5th avenue clinic",
        "start": 79,
        "end": 96
      }
    ],
    "status": "LEAK_DETECTED"
  },
  "metrics": {
    "total_phi_entities": 3,
    "successfully_redacted": 2,
    "leaked_failures": 1,
    "total_detected": 2,
    "recall": "0.6667",
    "precision": "1.0000",
    "f1_score": "0.8000"
  }
}